flask_esearch/__init__.py
Flask_ESearch-0.5.0.dist-info/AUTHORS.md
Flask_ESearch-0.5.0.dist-info/LICENSE
Flask_ESearch-0.5.0.dist-info/METADATA
Flask_ESearch-0.5.0.dist-info/WHEEL
Flask_ESearch-0.5.0.dist-info/top_level.txt
Flask_ESearch-0.5.0.dist-info/RECORD
