Metadata-Version: 2.1
Name: Flask-ESearch
Version: 0.5.0
Summary: Extension of Elasticsearch for Flask with a simple integration
Home-page: https://github.com/dymmond/flask-esearch
Author: Tiago Silva
Author-email: tiago.silva@dymmond.com
License: MIT
Platform: any
Classifier: Framework :: Flask
Classifier: Environment :: Web Environment
Classifier: Intended Audience :: Developers
Classifier: License :: OSI Approved :: MIT License
Classifier: Operating System :: OS Independent
Classifier: Programming Language :: Python :: 3.8
Classifier: Programming Language :: Python :: 3.9
Classifier: Programming Language :: Python :: 3.10
Classifier: Programming Language :: Python :: 3.11
Classifier: Programming Language :: Python :: 3.12
Classifier: Topic :: Internet :: WWW/HTTP :: Dynamic Content
Classifier: Topic :: Software Development :: Libraries :: Python Modules
License-File: LICENSE
License-File: AUTHORS.md
Requires-Dist: Flask >=2.3.0
Requires-Dist: Elasticsearch >=6.4.6
Requires-Dist: Elasticsearch-dsl >=6.4.6
